nisdc/__init__.py
nisdc/nisemidevicecontrol.py
nisdc-24.5.0.0.dist-info/LICENSE
nisdc-24.5.0.0.dist-info/METADATA
nisdc-24.5.0.0.dist-info/WHEEL
nisdc-24.5.0.0.dist-info/RECORD
