Metadata-Version: 2.1
Name: nisdc
Version: 24.5.0.0
Summary: NI Semiconductor Device Control python Support provides python APIs to develop python test programs and communicate with a device using the setup configuration exported from the Semiconductor Device Control Add-On for InstrumentStudio.
License: MIT
Author: National Instruments
Requires-Python: >=3.7,<3.13
Classifier: License :: OSI Approved :: MIT License
Classifier: Programming Language :: Python :: 3
Classifier: Programming Language :: Python :: 3.7
Classifier: Programming Language :: Python :: 3.8
Classifier: Programming Language :: Python :: 3.9
Classifier: Programming Language :: Python :: 3.10
Classifier: Programming Language :: Python :: 3.11
Requires-Dist: grpcio (==1.62.2)
Requires-Dist: protobuf (==4.24.4)
Requires-Dist: pythonnet (==3.0.3)
